Metadata-Version: 2.1
Name: mimesis-stats
Version: 0.1.1
Summary: Extension of mimesis library for data generation with statistical properties
Home-page: https://github.com/jonathonmellor/mimesis-stats
Author: Jonathon Mellor
Author-email: mellorjonathon1@gmail.com
License: UNKNOWN
Download-URL: https://github.com/jonathonmellor/mimesis-stats/archive/refs/tags/v0.1.1.tar.gz
Project-URL: Bug Tracker, https://github.com/jonathonmellor/mimesis-stats/issues
Platform: UNKNOWN
Classifier: Programming Language :: Python :: 3.6
Classifier: Programming Language :: Python :: 3.7
Classifier: Programming Language :: Python :: 3.8
Classifier: Programming Language :: Python :: 3.9
Classifier: License :: OSI Approved :: MIT License
Classifier: Operating System :: OS Independent
Requires-Python: >=3.6.8
Provides-Extra: dev
Provides-Extra: ci
